ast_compat/__init__.py
ast_compat/__init__.pyi
ast_compat/compat3k10_ast.py
ast_compat/compat3k10_unparse.py
ast_compat/compat3k11_ast.py
ast_compat/compat3k11_unparse.py
ast_compat/compat3k12_ast.py
ast_compat/compat3k12_unparse.py
ast_compat/compat3k13_ast.py
ast_compat/compat3k13_unparse.py
ast_compat/compat3k5_ast.py
ast_compat/compat3k5_unparse.py
ast_compat/compat3k6_ast.py
ast_compat/compat3k6_unparse.py
ast_compat/compat3k7_ast.py
ast_compat/compat3k7_unparse.py
ast_compat/compat3k8_ast.py
ast_compat/compat3k8_unparse.py
ast_compat/compat3k9_ast.py
ast_compat/compat3k9_unparse.py
ast_compat/make.py
tests/__init__.py
tests/test_ast_compat.py
ast_compat-0.12.0.dist-info/LICENSE
ast_compat-0.12.0.dist-info/METADATA
ast_compat-0.12.0.dist-info/WHEEL
ast_compat-0.12.0.dist-info/top_level.txt
ast_compat-0.12.0.dist-info/RECORD
