Metadata-Version: 2.1
Name: ast-compat
Version: 0.12.0
Summary: cross-version compatible ast library
Home-page: https://github.com/python-compiler-tools/ast-compat
Author: thautwarm
Author-email: twshere@outlook.com
License: mit
Keywords: ast compat
Platform: any
Classifier: Programming Language :: Python :: 3.5
Classifier: Programming Language :: Python :: 3.6
Classifier: Programming Language :: Python :: 3.7
Classifier: Programming Language :: Python :: 3.8
Classifier: Programming Language :: Python :: 3.9
Classifier: Programming Language :: Python :: 3.10
Classifier: Programming Language :: Python :: 3.11
Classifier: Programming Language :: Python :: 3.12
Classifier: Programming Language :: Python :: 3.13
Classifier: Programming Language :: Python :: Implementation :: CPython
Requires-Python: >=3.5
License-File: LICENSE
